Workbook

Sheet 📊 Dashboard
A1: Voucher App - QA Testing Dashboard
A3: Scope: Browser-based UI/UX Testing | Version: 1.0 | Last Updated: 20 April, 2026
B5: Section | C5: Total Tests | D5: Passed ✅ | E5: Failed ❌ | F5: Not Run ⬜ | G5: Pass Rate | H5: Status
B6: 1. UI/Visual Testing | C6: =COUNTIF('1.UI Visual'!G:G,"Pass")+COUNTIF('1.UI Visual'!G:G,"Fail")+COUNTIF('1.UI Visual'!G:G,"Not Run") -> 50 | D6: =COUNTIF('1.UI Visual'!G:G,"Pass") -> 48 | E6: =COUNTIF('1.UI Visual'!G:G,"Fail") -> 1 | F6: =COUNTIF('1.UI Visual'!G:G,"Not Run") -> 1 | G6: =IFERROR(D6/C6,0) -> 0.96 | H6: =IF(E6>0,"❌ Has Failures",IF(F6>0,"⚠️ Incomplete","✅ Complete")) -> ❌ Has Failures
B7: 2. Functional Testing | C7: =COUNTIF('2.Functional'!G:G,"Pass")+COUNTIF('2.Functional'!G:G,"Fail")+COUNTIF('2.Functional'!G:G,"Not Run") -> 93 | D7: =COUNTIF('2.Functional'!G:G,"Pass") -> 61 | E7: =COUNTIF('2.Functional'!G:G,"Fail") -> 25 | F7: =COUNTIF('2.Functional'!G:G,"Not Run") -> 7 | G7: =IFERROR(D7/C7,0) -> 0.65591398 | H7: =IF(E7>0,"❌ Has Failures",IF(F7>0,"⚠️ Incomplete","✅ Complete")) -> ❌ Has Failures
B8: 3. Responsive Testing | C8: =COUNTIF('3.Responsive'!G:G,"Pass")+COUNTIF('3.Responsive'!G:G,"Fail")+COUNTIF('3.Responsive'!G:G,"Not Run") -> 42 | D8: =COUNTIF('3.Responsive'!G:G,"Pass") -> 35 | E8: =COUNTIF('3.Responsive'!G:G,"Fail") -> 7 | F8: =COUNTIF('3.Responsive'!G:G,"Not Run") -> 0 | G8: =IFERROR(D8/C8,0) -> 0.83333333 | H8: =IF(E8>0,"❌ Has Failures",IF(F8>0,"⚠️ Incomplete","✅ Complete")) -> ❌ Has Failures
B9: 4. Cross-Browser Testing | C9: =COUNTIF('4.CrossBrowser'!G:G,"Pass")+COUNTIF('4.CrossBrowser'!G:G,"Fail")+COUNTIF('4.CrossBrowser'!G:G,"Not Run") -> 37 | D9: =COUNTIF('4.CrossBrowser'!G:G,"Pass") -> 9 | E9: =COUNTIF('4.CrossBrowser'!G:G,"Fail") -> 28 | F9: =COUNTIF('4.CrossBrowser'!G:G,"Not Run") -> 0 | G9: =IFERROR(D9/C9,0) -> 0.24324324 | H9: =IF(E9>0,"❌ Has Failures",IF(F9>0,"⚠️ Incomplete","✅ Complete")) -> ❌ Has Failures
B10: 5. Accessibility Testing | C10: =COUNTIF('5.Accessibility'!G:G,"Pass")+COUNTIF('5.Accessibility'!G:G,"Fail")+COUNTIF('5.Accessibility'!G:G,"Not Run") -> 46 | D10: =COUNTIF('5.Accessibility'!G:G,"Pass") -> 39 | E10: =COUNTIF('5.Accessibility'!G:G,"Fail") -> 5 | F10: =COUNTIF('5.Accessibility'!G:G,"Not Run") -> 2 | G10: =IFERROR(D10/C10,0) -> 0.84782609 | H10: =IF(E10>0,"❌ Has Failures",IF(F10>0,"⚠️ Incomplete","✅ Complete")) -> ❌ Has Failures
B11: 6. Performance Testing | C11: =COUNTIF('6.Performance'!G:G,"Pass")+COUNTIF('6.Performance'!G:G,"Fail")+COUNTIF('6.Performance'!G:G,"Not Run") -> 43 | D11: =COUNTIF('6.Performance'!G:G,"Pass") -> 27 | E11: =COUNTIF('6.Performance'!G:G,"Fail") -> 9 | F11: =COUNTIF('6.Performance'!G:G,"Not Run") -> 7 | G11: =IFERROR(D11/C11,0) -> 0.62790698 | H11: =IF(E11>0,"❌ Has Failures",IF(F11>0,"⚠️ Incomplete","✅ Complete")) -> ❌ Has Failures
B12: GRAND TOTAL | C12: =SUM(C6:C11) -> 311 | D12: =SUM(D6:D11) -> 219 | E12: =SUM(E6:E11) -> 75 | F12: =SUM(F6:F11) -> 17 | G12: =IFERROR(D12/C12,0) -> 0.70418006 | H12: =IF(E12>0,"❌ FAIL",IF(D12/C12>=0.95,"✅ PASS","⚠️ CONDITIONAL")) -> ❌ FAIL
B14: 📋 PASS/FAIL CRITERIA
B15: ✅ PASS | C15: All Critical tests pass + ≥ 95% total pass rate → Ready for Production
B16: ⚠️ CONDITIONAL | C16: All Critical tests pass + ≥ 90% pass rate → Fix minor issues, deploy
B17: ❌ FAIL | C17: Any Critical test fails OR < 90% total pass rate → Fix and retest
B19: 🔴🟡🟢🔵 PRIORITY DEFINITIONS
B20: 🔴 Critical | C20: Blocks core functionality, security, data loss | H20: Must pass all
B21: 🟡 High | C21: Major feature broken, workaround exists | H21: Should pass
B22: 🟢 Medium | C22: Minor issue, cosmetic problem | H22: Nice to pass
B23: 🔵 Low | C23: Enhancement, edge case | H23: Optional

Sheet 1.UI Visual
A1: 1.UI Visual
A2: Use dropdown in "Result" column: Pass / Fail / Not Run / Blocked
A4: Test ID | B4: Test Case Description | C4: Page / Component | D4: Priority | E4: Pass | F4: Fail | G4: Result | H4: Notes / Bug Reference | I4: Tester
A5: 1.1 Layout & Structure
A6: 1.1.1 | B6: Grid alignment consistent across all sections | C6: Homepage | D6: 🟢 Medium | E6: =IF(G6="Pass","✅","") -> ✅ | F6: =IF(G6="Fail","❌","") | G6: Pass | I6: Subhendu
A7: 1.1.2 | B7: No horizontal scrollbar on desktop | C7: All pages | D7: 🔴 Critical | E7: =IF(G7="Pass","✅","") -> ✅ | F7: =IF(G7="Fail","❌","") | G7: Pass | I7: Subhendu
A8: 1.1.3 | B8: Proper spacing between elements (padding/margin) | C8: Register Page | D8: 🟢 Medium | E8: =IF(G8="Pass","✅","") -> ✅ | F8: =IF(G8="Fail","❌","") | G8: Pass | H8: Improper padding/margin on the Register page causes text elements to stick together. | I8: Subhendu
A9: 1.1.4 | B9: Cards/components aligned properly | C9: Product/Voucher listing | D9: 🟡 High | E9: =IF(G9="Pass","✅","") -> ✅ | F9: =IF(G9="Fail","❌","") | G9: Pass | I9: Subhendu
A10: 1.1.5 | B10: Footer consistent across all pages | C10: Global | D10: 🟢 Medium | E10: =IF(G10="Pass","✅","") -> ✅ | F10: =IF(G10="Fail","❌","") | G10: Pass | I10: Subhendu
A11: 1.1.6 | B11: Navigation menu items properly spaced | C11: Header/Navbar | D11: 🟢 Medium | E11: =IF(G11="Pass","✅","") -> ✅ | F11: =IF(G11="Fail","❌","") | G11: Pass | I11: Subhendu
A12: 1.1.7 | B12: Sidebar navigation aligned (admin/customer) | C12: Dashboard | D12: 🟡 High | E12: =IF(G12="Pass","✅","") -> ✅ | F12: =IF(G12="Fail","❌","") | G12: Pass | I12: Subhendu
A13: 1.1.8 | B13: Modal dialogs centered properly | C13: All modals | D13: 🟡 High | E13: =IF(G13="Pass","✅","") -> ✅ | F13: =IF(G13="Fail","❌","") | G13: Pass | I13: Subhendu
A14: 1.1.9 | B14: Tables responsive with proper column widths | C14: Admin listings | D14: 🟡 High | E14: =IF(G14="Pass","✅","") -> ✅ | F14: =IF(G14="Fail","❌","") | G14: Pass | I14: Subhendu
A15: 1.1.10 | B15: No overlapping text or elements | C15: All pages | D15: 🔴 Critical | E15: =IF(G15="Pass","✅","") -> ✅ | F15: =IF(G15="Fail","❌","") | G15: Pass | I15: Subhendu
A16: 1.2 Colors & Branding
A17: 1.2.1 | B17: Primary brand color consistent | C17: All pages | D17: 🟡 High | E17: =IF(G17="Pass","✅","") -> ✅ | F17: =IF(G17="Fail","❌","") | G17: Pass | I17: Subhendu
A18: 1.2.2 | B18: Button colors follow design system | C18: All buttons | D18: 🟡 High | E18: =IF(G18="Pass","✅","") -> ✅ | F18: =IF(G18="Fail","❌","") | G18: Pass | I18: Subhendu
A19: 1.2.3 | B19: Link colors consistent (visited/hover/active) | C19: All links | D19: 🟢 Medium | E19: =IF(G19="Pass","✅","") -> ✅ | F19: =IF(G19="Fail","❌","") | G19: Pass | I19: Subhendu
A20: 1.2.4 | B20: Error messages in red (#dc2626 or similar) | C20: Forms | D20: 🟡 High | E20: =IF(G20="Pass","✅","") -> ✅ | F20: =IF(G20="Fail","❌","") | G20: Pass | I20: Subhendu
A21: 1.2.5 | B21: Success messages in green | C21: Notifications | D21: 🟡 High | E21: =IF(G21="Pass","✅","") -> ✅ | F21: =IF(G21="Fail","❌","") | G21: Pass | I21: Subhendu
A22: 1.2.6 | B22: Warning messages in yellow/orange | C22: Notifications | D22: 🟢 Medium | E22: =IF(G22="Pass","✅","") -> ✅ | F22: =IF(G22="Fail","❌","") | G22: Pass | I22: Subhendu
A23: 1.2.7 | B23: Background colors consistent | C23: All pages | D23: 🟢 Medium | E23: =IF(G23="Pass","✅","") -> ✅ | F23: =IF(G23="Fail","❌","") | G23: Pass | I23: Subhendu
A24: 1.2.8 | B24: Logo displays correctly with proper colors | C24: Header | D24: 🟡 High | E24: =IF(G24="Pass","✅","") -> ✅ | F24: =IF(G24="Fail","❌","") | G24: Pass | I24: Subhendu
A25: 1.2.9 | B25: Gradient effects render smoothly | C25: Hero sections | D25: 🔵 Low | E25: =IF(G25="Pass","✅","") -> ✅ | F25: =IF(G25="Fail","❌","") | G25: Pass | I25: Subhendu
A26: 1.2.10 | B26: Dark/Light mode colors correct (if applicable) | C26: Theme toggle | D26: 🔵 Low | E26: =IF(G26="Pass","✅","") -> ✅ | F26: =IF(G26="Fail","❌","") | G26: Pass | I26: Subhendu
A27: 1.3 Typography & Fonts
A28: 1.3.1 | B28: Font family consistent across site | C28: All pages | D28: 🟡 High | E28: =IF(G28="Pass","✅","") -> ✅ | F28: =IF(G28="Fail","❌","") | G28: Pass | I28: Subhendu
A29: 1.3.2 | B29: Heading hierarchy (H1–H6) proper sizes | C29: All pages | D29: 🟡 High | E29: =IF(G29="Pass","✅","") -> ✅ | F29: =IF(G29="Fail","❌","") | G29: Pass | I29: Subhendu
A30: 1.3.3 | B30: Body text readable (minimum 14px) | C30: All pages | D30: 🔴 Critical | E30: =IF(G30="Pass","✅","") -> ✅ | F30: =IF(G30="Fail","❌","") | G30: Pass | I30: Subhendu
A31: 1.3.4 | B31: Font weights correct (bold, regular, light) | C31: All text | D31: 🟢 Medium | E31: =IF(G31="Pass","✅","") -> ✅ | F31: =IF(G31="Fail","❌","") | G31: Pass | H31: Certain font weights on the registration page are appearing bold and require adjustment for visual consistency. | I31: Subhendu
A32: 1.3.5 | B32: Line height comfortable for reading | C32: All text blocks | D32: 🟢 Medium | E32: =IF(G32="Pass","✅","") -> ✅ | F32: =IF(G32="Fail","❌","") | G32: Pass | I32: Subhendu
A33: 1.3.6 | B33: No text clipping or truncation issues | C33: Buttons/Labels | D33: 🟡 High | E33: =IF(G33="Pass","✅","") -> ✅ | F33: =IF(G33="Fail","❌","") | G33: Pass | I33: Subhendu
A34: 1.3.7 | B34: Special characters display correctly | C34: All languages | D34: 🟡 High | E34: =IF(G34="Pass","✅","") -> ✅ | F34: =IF(G34="Fail","❌","") | G34: Pass | I34: Subhendu
A35: 1.3.8 | B35: Arabic/Farsi text renders RTL correctly | C35: Arabic pages | D35: 🟡 High | E35: =IF(G35="Pass","✅","") -> ✅ | F35: =IF(G35="Fail","❌","") | G35: Pass | I35: Subhendu
A36: 1.3.9 | B36: Spanish characters (ñ, á, é) display correctly | C36: Spanish pages | D36: 🟡 High | E36: =IF(G36="Pass","✅","") -> ✅ | F36: =IF(G36="Fail","❌","") | G36: Pass | I36: Subhendu
A37: 1.3.10 | B37: Custom fonts load without FOUT/FOIT | C37: All pages | D37: 🟢 Medium | E37: =IF(G37="Pass","✅","") -> ✅ | F37: =IF(G37="Fail","❌","") | G37: Pass | I37: Subhendu
A38: 1.4 Images & Icons
A39: 1.4.1 | B39: Logo displays without distortion | C39: Header | D39: 🟡 High | E39: =IF(G39="Pass","✅","") -> ✅ | F39: =IF(G39="Fail","❌","") | G39: Pass | I39: Subhendu
A40: 1.4.2 | B40: Product images load correctly | C40: Product listing | D40: 🔴 Critical | E40: =IF(G40="Pass","✅","") -> ✅ | F40: =IF(G40="Fail","❌","") | G40: Pass | I40: Subhendu
A41: 1.4.3 | B41: Images have proper aspect ratios | C41: All images | D41: 🟢 Medium | E41: =IF(G41="Pass","✅","") -> ✅ | F41: =IF(G41="Fail","❌","") | G41: Pass | I41: Subhendu
A42: 1.4.4 | B42: Icons render correctly (FontAwesome) | C42: All icons | D42: 🟢 Medium | E42: =IF(G42="Pass","✅","") -> ✅ | F42: =IF(G42="Fail","❌","") | G42: Pass | I42: Subhendu
A43: 1.4.5 | B43: Icon sizes consistent throughout | C43: All icons | D43: 🟢 Medium | E43: =IF(G43="Pass","✅","") -> ✅ | F43: =IF(G43="Fail","❌","") | G43: Pass | I43: Subhendu
A44: 1.4.6 | B44: Image alt text present | C44: All images | D44: 🟡 High | E44: =IF(G44="Pass","✅","") -> ✅ | F44: =IF(G44="Fail","❌","") | G44: Pass | I44: Subhendu
A45: 1.4.7 | B45: Lazy loading works on image lists | C45: Product grids | D45: 🟢 Medium | E45: =IF(G45="Pass","✅","") -> ✅ | F45: =IF(G45="Fail","❌","") | G45: Pass | I45: Subhendu
A46: 1.4.8 | B46: Broken images show fallback | C46: Error handling | D46: 🟡 High | E46: =IF(G46="Pass","✅","") -> ✅ | F46: =IF(G46="Fail","❌","") | G46: Pass | H46: Broken images are appearing in the Enterprise Pricing Plan, Customer Reviews, Page & Content Builder (Features) and dashboard logos across all roles, requiring a proper fallback implementation. | I46: Subhendu
A47: 1.4.9 | B47: Background images scale properly | C47: Hero sections | D47: 🟢 Medium | E47: =IF(G47="Pass","✅","") -> ✅ | F47: =IF(G47="Fail","❌","") | G47: Pass | I47: Subhendu
A48: 1.4.10 | B48: QR codes generate and display clearly | C48: Voucher codes | D48: 🔴 Critical | E48: =IF(G48="Pass","✅","") | F48: =IF(G48="Fail","❌","") | G48: Not Run | I48: Subhendu
A49: 1.5 Animations & Transitions
A50: 1.5.1 | B50: Button hover effects smooth | C50: All buttons | D50: 🟢 Medium | E50: =IF(G50="Pass","✅","") -> ✅ | F50: =IF(G50="Fail","❌","") | G50: Pass | I50: Subhendu
A51: 1.5.2 | B51: Link hover effects present | C51: All links | D51: 🔵 Low | E51: =IF(G51="Pass","✅","") -> ✅ | F51: =IF(G51="Fail","❌","") | G51: Pass | I51: Subhendu
A52: 1.5.3 | B52: Dropdown menus animate smoothly | C52: Navigation | D52: 🟢 Medium | E52: =IF(G52="Pass","✅","") -> ✅ | F52: =IF(G52="Fail","❌","") | G52: Pass | H52: Navigation menus across all dashboards (Super Admin, Owner, Staff) remain expanded and fail to collapse after opening sub-menus. | I52: Subhendu
A53: 1.5.4 | B53: Modal open/close animations | C53: All modals | D53: 🟢 Medium | E53: =IF(G53="Pass","✅","") -> ✅ | F53: =IF(G53="Fail","❌","") | G53: Pass | I53: Subhendu
A54: 1.5.5 | B54: Loading spinners display correctly | C54: Async actions | D54: 🟡 High | E54: =IF(G54="Pass","✅","") -> ✅ | F54: =IF(G54="Fail","❌","") | G54: Pass | I54: Subhendu
A55: 1.5.6 | B55: Toast notifications slide in/out | C55: Notifications | D55: 🟢 Medium | E55: =IF(G55="Pass","✅","") -> ✅ | F55: =IF(G55="Fail","❌","") | G55: Pass | I55: Subhendu
A56: 1.5.7 | B56: Form validation animations | C56: Form fields | D56: 🟢 Medium | E56: =IF(G56="Pass","✅","") -> ✅ | F56: =IF(G56="Fail","❌","") | G56: Pass | I56: Subhendu
A57: 1.5.8 | B57: Page transitions smooth | C57: Navigation | D57: 🔵 Low | E57: =IF(G57="Pass","✅","") -> ✅ | F57: =IF(G57="Fail","❌","") | G57: Pass | I57: Subhendu
A58: 1.5.9 | B58: Wheel spin animation works | C58: Wheel popup | D58: 🟡 High | E58: =IF(G58="Pass","✅","") | F58: =IF(G58="Fail","❌","") -> ❌ | G58: Fail | H58: The Wheel Spin popup fails to trigger automatically upon page load as intended. | I58: Subhendu
A59: 1.5.10 | B59: No janky or stuttering animations | C59: All animations | D59: 🟢 Medium | E59: =IF(G59="Pass","✅","") -> ✅ | F59: =IF(G59="Fail","❌","") | G59: Pass | I59: Subhendu
A61: 📊 Section Summary | C61: Total | D61: Passed | E61: Failed | F61: Not Run | G61: Pass Rate
C62: =COUNTA(G5:G59) -> 50 | D62: =COUNTIF(G5:G59,"Pass") -> 48 | E62: =COUNTIF(G5:G59,"Fail") -> 1 | F62: =COUNTIF(G5:G59,"Not Run") -> 1 | G62: =IFERROR(COUNTIF(G5:G59,"Pass")/COUNTA(G5:G59),0) -> 0.96

Sheet 2.Functional
A1: 2.Functional
A2: Use dropdown in "Result" column: Pass / Fail / Not Run / Blocked
A4: Test ID | B4: Test Case Description | C4: Page / Component | D4: Priority | E4: Pass | F4: Fail | G4: Result | H4: Notes / Bug Reference | I4: Tester
A5: 2.1 Navigation & Routing
A6: 2.1.1 | B6: Logo click redirects to homepage | C6: Header | D6: 🔴 Critical | E6: =IF(G6="Pass","✅","") -> ✅ | F6: =IF(G6="Fail","❌","") | G6: Pass | I6: Subhendu
A7: 2.1.2 | B7: Main navigation links work | C7: Header | D7: 🔴 Critical | E7: =IF(G7="Pass","✅","") -> ✅ | F7: =IF(G7="Fail","❌","") | G7: Pass | I7: Subhendu
A8: 2.1.3 | B8: Footer links functional | C8: Footer | D8: 🟡 High | E8: =IF(G8="Pass","✅","") | F8: =IF(G8="Fail","❌","") -> ❌ | G8: Fail | H8: The newsletter subscription field is non-functional and fails to process or send email submissions. | I8: Subhendu
A9: 2.1.4 | B9: Breadcrumbs navigate correctly | C9: All pages | D9: 🟡 High | E9: =IF(G9="Pass","✅","") -> ✅ | F9: =IF(G9="Fail","❌","") | G9: Pass | I9: Subhendu
A10: 2.1.5 | B10: Back button works as expected | C10: Browser | D10: 🟡 High | E10: =IF(G10="Pass","✅","") -> ✅ | F10: =IF(G10="Fail","❌","") | G10: Pass | I10: Subhendu
A11: 2.1.6 | B11: 404 page displays for invalid URLs | C11: Error pages | D11: 🟡 High | E11: =IF(G11="Pass","✅","") -> ✅ | F11: =IF(G11="Fail","❌","") | G11: Pass | I11: Subhendu
A12: 2.1.7 | B12: Admin sidebar navigation works | C12: Admin panel | D12: 🔴 Critical | E12: =IF(G12="Pass","✅","") -> ✅ | F12: =IF(G12="Fail","❌","") | G12: Pass | H12: Navigation menus across all dashboards (Super Admin, Owner, Staff) remain expanded and fail to collapse after opening sub-menus. | I12: Subhendu
A13: 2.1.8 | B13: Customer portal navigation works | C13: Customer panel | D13: 🔴 Critical | E13: =IF(G13="Pass","✅","") -> ✅ | F13: =IF(G13="Fail","❌","") | G13: Pass | H13: Navigation menus across all dashboards (Super Admin, Owner, Staff) remain expanded and fail to collapse after opening sub-menus. | I13: Subhendu
A14: 2.1.9 | B14: Language switcher changes pages | C14: Language dropdown | D14: 🟡 High | E14: =IF(G14="Pass","✅","") -> ✅ | F14: =IF(G14="Fail","❌","") | G14: Pass | I14: Subhendu
A15: 2.1.10 | B15: Currency switcher updates prices | C15: Currency dropdown | D15: 🟡 High | E15: =IF(G15="Pass","✅","") -> ✅ | F15: =IF(G15="Fail","❌","") | G15: Pass | I15: Subhendu
A16: 2.2 Forms & Input Fields
A17: 2.2.1 | B17: Login form validates email format | C17: Login page | D17: 🔴 Critical | E17: =IF(G17="Pass","✅","") -> ✅ | F17: =IF(G17="Fail","❌","") | G17: Pass | I17: Subhendu
A18: 2.2.2 | B18: Login form validates password required | C18: Login page | D18: 🔴 Critical | E18: =IF(G18="Pass","✅","") -> ✅ | F18: =IF(G18="Fail","❌","") | G18: Pass | I18: Subhendu
A19: 2.2.3 | B19: Login form shows errors for invalid credentials | C19: Login page | D19: 🔴 Critical | E19: =IF(G19="Pass","✅","") -> ✅ | F19: =IF(G19="Fail","❌","") | G19: Pass | I19: Subhendu
A20: 2.2.4 | B20: Registration form validates all fields | C20: Register page | D20: 🔴 Critical | E20: =IF(G20="Pass","✅","") -> ✅ | F20: =IF(G20="Fail","❌","") | G20: Pass | H20: Missing mandatory validation for the phone number field. | I20: Subhendu
A21: 2.2.5 | B21: Registration form checks email uniqueness | C21: Register page | D21: 🔴 Critical | E21: =IF(G21="Pass","✅","") -> ✅ | F21: =IF(G21="Fail","❌","") | G21: Pass | I21: Subhendu
A22: 2.2.6 | B22: Registration form password strength indicator | C22: Register page | D22: 🟡 High | E22: =IF(G22="Pass","✅","") | F22: =IF(G22="Fail","❌","") -> ❌ | G22: Fail | H22: Missing password strength indicator in the registration form. | I22: Subhendu
A23: 2.2.7 | B23: Password visibility toggle (eye icon) works | C23: All password fields | D23: 🟡 High | E23: =IF(G23="Pass","✅","") -> ✅ | F23: =IF(G23="Fail","❌","") | G23: Pass | I23: Subhendu
A24: 2.2.8 | B24: Email settings password field optional | C24: Admin Email Settings | D24: 🟡 High | E24: =IF(G24="Pass","✅","") | F24: =IF(G24="Fail","❌","") -> ❌ | G24: Fail | H24: Password updates without validation and lacks success notification. | I24: Subhendu
A25: 2.2.9 | B25: Form auto-focus on first field | C25: All forms | D25: 🟢 Medium | E25: =IF(G25="Pass","✅","") | F25: =IF(G25="Fail","❌","") -> ❌ | G25: Fail | H25: First input field fails to auto-focus upon form or page load. | I25: Subhendu
A26: 2.2.10 | B26: Tab order logical through form | C26: All forms | D26: 🟡 High | E26: =IF(G26="Pass","✅","") -> ✅ | F26: =IF(G26="Fail","❌","") | G26: Pass | I26: Subhendu
A27: 2.2.11 | B27: Required fields marked with asterisk | C27: All forms | D27: 🟢 Medium | E27: =IF(G27="Pass","✅","") | F27: =IF(G27="Fail","❌","") -> ❌ | G27: Fail | H27: Missing mandatory asterisks (*) for required input fields. | I27: Subhendu
A28: 2.2.12 | B28: Validation errors display inline | C28: All forms | D28: 🟡 High | E28: =IF(G28="Pass","✅","") -> ✅ | F28: =IF(G28="Fail","❌","") | G28: Pass | I28: Subhendu
A29: 2.2.13 | B29: Form submission shows loading state | C29: All forms | D29: 🟡 High | E29: =IF(G29="Pass","✅","") -> ✅ | F29: =IF(G29="Fail","❌","") | G29: Pass | I29: Subhendu
A30: 2.2.14 | B30: Success messages display after submit | C30: All forms | D30: 🟡 High | E30: =IF(G30="Pass","✅","") -> ✅ | F30: =IF(G30="Fail","❌","") | G30: Pass | I30: Subhendu
A31: 2.2.15 | B31: Form data persists on validation error | C31: All forms | D31: 🟡 High | E31: =IF(G31="Pass","✅","") -> ✅ | F31: =IF(G31="Fail","❌","") | G31: Pass | I31: Subhendu
A32: 2.3 Buttons & Actions
A33: 2.3.1 | B33: Primary buttons visually distinct | C33: All pages | D33: 🟡 High | E33: =IF(G33="Pass","✅","") -> ✅ | F33: =IF(G33="Fail","❌","") | G33: Pass | I33: Subhendu
A34: 2.3.2 | B34: Button click shows loading state | C34: Async actions | D34: 🟡 High | E34: =IF(G34="Pass","✅","") -> ✅ | F34: =IF(G34="Fail","❌","") | G34: Pass | I34: Subhendu
A35: 2.3.3 | B35: Disabled buttons not clickable | C35: All disabled states | D35: 🔴 Critical | E35: =IF(G35="Pass","✅","") -> ✅ | F35: =IF(G35="Fail","❌","") | G35: Pass | I35: Subhendu
A36: 2.3.4 | B36: Delete actions show confirmation | C36: All delete buttons | D36: 🔴 Critical | E36: =IF(G36="Pass","✅","") -> ✅ | F36: =IF(G36="Fail","❌","") | G36: Pass | I36: Subhendu
A37: 2.3.5 | B37: Save buttons provide feedback | C37: All forms | D37: 🟡 High | E37: =IF(G37="Pass","✅","") -> ✅ | F37: =IF(G37="Fail","❌","") | G37: Pass | I37: Subhendu
A38: 2.3.6 | B38: Cancel buttons return to previous page | C38: All forms | D38: 🟡 High | E38: =IF(G38="Pass","✅","") -> ✅ | F38: =IF(G38="Fail","❌","") | G38: Pass | I38: Subhendu
A39: 2.3.7 | B39: Test Email button sends test email | C39: Email Settings | D39: 🟡 High | E39: =IF(G39="Pass","✅","") | F39: =IF(G39="Fail","❌","") | G39: Not Run
A40: 2.3.8 | B40: Add to Cart button updates cart count | C40: Product pages | D40: 🔴 Critical | E40: =IF(G40="Pass","✅","") -> ✅ | F40: =IF(G40="Fail","❌","") | G40: Pass | I40: Subhendu
A41: 2.3.9 | B41: Checkout button proceeds to payment | C41: Cart page | D41: 🔴 Critical | E41: =IF(G41="Pass","✅","") | F41: =IF(G41="Fail","❌","") -> ❌ | G41: Fail | H41: Internal Server Error | I41: Subhendu
A42: 2.3.10 | B42: Export/Download buttons generate files | C42: Admin panels | D42: 🟡 High | E42: =IF(G42="Pass","✅","") | F42: =IF(G42="Fail","❌","") -> ❌ | G42: Fail | H42: Export/Download functionality is not implemented in the Admin panel. | I42: Subhendu
A43: 2.4 Shopping Cart & Checkout
A44: 2.4.1 | B44: Add to Cart from product listing | C44: Product grid | D44: 🔴 Critical | E44: =IF(G44="Pass","✅","") -> ✅ | F44: =IF(G44="Fail","❌","") | G44: Pass | I44: Subhendu
A45: 2.4.2 | B45: Add to Cart from product detail | C45: Product page | D45: 🔴 Critical | E45: =IF(G45="Pass","✅","") | F45: =IF(G45="Fail","❌","") -> ❌ | G45: Fail | H45: Internal Server Error | I45: Subhendu
A46: 2.4.3 | B46: Cart count updates in header | C46: Global header | D46: 🔴 Critical | E46: =IF(G46="Pass","✅","") -> ✅ | F46: =IF(G46="Fail","❌","") | G46: Pass | I46: Subhendu
A47: 2.4.4 | B47: Cart page shows all added items | C47: Cart page | D47: 🔴 Critical | E47: =IF(G47="Pass","✅","") -> ✅ | F47: =IF(G47="Fail","❌","") | G47: Pass | I47: Subhendu
A48: 2.4.5 | B48: Quantity update recalculates total | C48: Cart page | D48: 🔴 Critical | E48: =IF(G48="Pass","✅","") -> ✅ | F48: =IF(G48="Fail","❌","") | G48: Pass | I48: Subhendu
A49: 2.4.6 | B49: Remove item from cart works | C49: Cart page | D49: 🔴 Critical | E49: =IF(G49="Pass","✅","") -> ✅ | F49: =IF(G49="Fail","❌","") | G49: Pass | I49: Subhendu
A50: 2.4.7 | B50: Empty cart shows appropriate message | C50: Cart page | D50: 🟡 High | E50: =IF(G50="Pass","✅","") -> ✅ | F50: =IF(G50="Fail","❌","") | G50: Pass | I50: Subhendu
A51: 2.4.8 | B51: Promo code apply shows discount | C51: Cart/Checkout | D51: 🟡 High | E51: =IF(G51="Pass","✅","") | F51: =IF(G51="Fail","❌","") -> ❌ | G51: Fail | H51: Promo code application fails with a backend fatal error: "Call to undefined method applyToOrder() | I51: Subhendu
A52: 2.4.9 | B52: Invalid promo code shows error | C52: Cart/Checkout | D52: 🟡 High | E52: =IF(G52="Pass","✅","") | F52: =IF(G52="Fail","❌","") -> ❌ | G52: Fail | H52: Promo code application fails with a backend fatal error: "Call to undefined method applyToOrder() | I52: Subhendu
A53: 2.4.10 | B53: Checkout form validates all fields | C53: Checkout page | D53: 🔴 Critical | E53: =IF(G53="Pass","✅","") | F53: =IF(G53="Fail","❌","") -> ❌ | G53: Fail | H53: Internal Server Error | I53: Subhendu
A54: 2.4.11 | B54: Order summary accurate | C54: Checkout page | D54: 🔴 Critical | E54: =IF(G54="Pass","✅","") | F54: =IF(G54="Fail","❌","") -> ❌ | G54: Fail | H54: Internal Server Error | I54: Subhendu
A55: 2.4.12 | B55: Payment gateway redirects correctly | C55: Payment page | D55: 🔴 Critical | E55: =IF(G55="Pass","✅","") | F55: =IF(G55="Fail","❌","") -> ❌ | G55: Fail | H55: Internal Server Error | I55: Subhendu
A56: 2.4.13 | B56: Order success page displays | C56: Order confirmation | D56: 🔴 Critical | E56: =IF(G56="Pass","✅","") | F56: =IF(G56="Fail","❌","") -> ❌ | G56: Fail | H56: Internal Server Error | I56: Subhendu
A57: 2.4.14 | B57: Voucher codes displayed after purchase | C57: Order confirmation | D57: 🔴 Critical | E57: =IF(G57="Pass","✅","") | F57: =IF(G57="Fail","❌","") -> ❌ | G57: Fail | H57: Internal Server Error | I57: Subhendu
A58: 2.4.15 | B58: Email confirmation received | C58: Email inbox | D58: 🔴 Critical | E58: =IF(G58="Pass","✅","") | F58: =IF(G58="Fail","❌","") -> ❌ | G58: Fail | H58: Internal Server Error | I58: Subhendu
A59: 2.5 Search & Filtering
A60: 2.5.1 | B60: Search bar accepts input | C60: Header | D60: 🟡 High | E60: =IF(G60="Pass","✅","") -> ✅ | F60: =IF(G60="Fail","❌","") | G60: Pass | I60: Subhendu
A61: 2.5.2 | B61: Search returns relevant results | C61: Search results | D61: 🟡 High | E61: =IF(G61="Pass","✅","") -> ✅ | F61: =IF(G61="Fail","❌","") | G61: Pass | I61: Subhendu
A62: 2.5.3 | B62: Empty search shows all or hint | C62: Search | D62: 🟢 Medium | E62: =IF(G62="Pass","✅","") -> ✅ | F62: =IF(G62="Fail","❌","") | G62: Pass | I62: Subhendu
A63: 2.5.4 | B63: Category filter works | C63: Product listing | D63: 🟡 High | E63: =IF(G63="Pass","✅","") -> ✅ | F63: =IF(G63="Fail","❌","") | G63: Pass | I63: Subhendu
A64: 2.5.5 | B64: Price range filter works | C64: Product listing | D64: 🟡 High | E64: =IF(G64="Pass","✅","") | F64: =IF(G64="Fail","❌","") -> ❌ | G64: Fail | H64: Missing price range filter functionality. | I64: Subhendu
A65: 2.5.6 | B65: Sort by (price, name, date) works | C65: Product listing | D65: 🟡 High | E65: =IF(G65="Pass","✅","") -> ✅ | F65: =IF(G65="Fail","❌","") | G65: Pass | H65: Missing Name and Date sorting options in the Sort by filter. | I65: Subhendu
A66: 2.5.7 | B66: Multiple filters combine correctly | C66: Product listing | D66: 🟡 High | E66: =IF(G66="Pass","✅","") | F66: =IF(G66="Fail","❌","") -> ❌ | G66: Fail | H66: Navigation filters (New Vouchers, Popular, Ending Soon) are non-functional and fail to filter results. | I66: Subhendu
A67: 2.5.8 | B67: Clear filters button resets all | C67: Product listing | D67: 🟡 High | E67: =IF(G67="Pass","✅","") -> ✅ | F67: =IF(G67="Fail","❌","") | G67: Pass | I67: Subhendu
A68: 2.5.9 | B68: Search results pagination works | C68: Search results | D68: 🟡 High | E68: =IF(G68="Pass","✅","") -> ✅ | F68: =IF(G68="Fail","❌","") | G68: Pass | I68: Subhendu
A69: 2.5.10 | B69: No results message displays | C69: Empty results | D69: 🟢 Medium | E69: =IF(G69="Pass","✅","") -> ✅ | F69: =IF(G69="Fail","❌","") | G69: Pass | I69: Subhendu
A70: 2.6 User Account & Profile
A71: 2.6.1 | B71: Login redirects to dashboard | C71: Login page | D71: 🔴 Critical | E71: =IF(G71="Pass","✅","") -> ✅ | F71: =IF(G71="Fail","❌","") | G71: Pass | I71: Subhendu
A72: 2.6.2 | B72: Logout clears session | C72: All pages | D72: 🔴 Critical | E72: =IF(G72="Pass","✅","") -> ✅ | F72: =IF(G72="Fail","❌","") | G72: Pass | I72: Subhendu
A73: 2.6.3 | B73: Profile edit saves changes | C73: Profile page | D73: 🟡 High | E73: =IF(G73="Pass","✅","") -> ✅ | F73: =IF(G73="Fail","❌","") | G73: Pass | I73: Subhendu
A74: 2.6.4 | B74: Password change works | C74: Profile/Security | D74: 🔴 Critical | E74: =IF(G74="Pass","✅","") -> ✅ | F74: =IF(G74="Fail","❌","") | G74: Pass | I74: Subhendu
A75: 2.6.5 | B75: Order history displays correctly | C75: Customer portal | D75: 🟡 High | E75: =IF(G75="Pass","✅","") | F75: =IF(G75="Fail","❌","") | G75: Not Run
A76: 2.6.6 | B76: Voucher codes accessible | C76: Customer portal | D76: 🔴 Critical | E76: =IF(G76="Pass","✅","") | F76: =IF(G76="Fail","❌","") | G76: Not Run
A77: 2.6.7 | B77: Support tickets CRUD works | C77: Customer portal | D77: 🟡 High | E77: =IF(G77="Pass","✅","") | F77: =IF(G77="Fail","❌","") -> ❌ | G77: Fail | H77: The "Close" button for support tickets is non-functional, preventing the finalization of ticket status. | I77: Subhendu
A78: 2.6.8 | B78: GDPR data export downloads | C78: Settings | D78: 🟡 High | E78: =IF(G78="Pass","✅","") -> ✅ | F78: =IF(G78="Fail","❌","") | G78: Pass | I78: Subhendu
A79: 2.6.9 | B79: Account deletion request works | C79: Settings | D79: 🟡 High | E79: =IF(G79="Pass","✅","") -> ✅ | F79: =IF(G79="Fail","❌","") | G79: Pass | I79: Subhendu
A80: 2.6.10 | B80: Email verification flow works | C80: Registration | D80: 🔴 Critical | E80: =IF(G80="Pass","✅","") | F80: =IF(G80="Fail","❌","") -> ❌ | G80: Fail | H80: Registration flow is incomplete due to missing email verification logic. | I80: Subhendu
A81: 2.7 Admin Panel Functions
A82: 2.7.1 | B82: Dashboard stats display correctly | C82: Admin Dashboard | D82: 🟡 High | E82: =IF(G82="Pass","✅","") -> ✅ | F82: =IF(G82="Fail","❌","") | G82: Pass | I82: Subhendu
A83: 2.7.2 | B83: User management CRUD works | C83: User Management | D83: 🔴 Critical | E83: =IF(G83="Pass","✅","") -> ✅ | F83: =IF(G83="Fail","❌","") | G83: Pass | I83: Subhendu
A84: 2.7.3 | B84: Business management CRUD works | C84: Business Module | D84: 🔴 Critical | E84: =IF(G84="Pass","✅","") -> ✅ | F84: =IF(G84="Fail","❌","") | G84: Pass | I84: Subhendu
A85: 2.7.4 | B85: Product/Voucher CRUD works | C85: Product Module | D85: 🔴 Critical | E85: =IF(G85="Pass","✅","") -> ✅ | F85: =IF(G85="Fail","❌","") | G85: Pass | I85: Subhendu
A86: 2.7.5 | B86: Order management works | C86: Order Module | D86: 🔴 Critical | E86: =IF(G86="Pass","✅","") -> ✅ | F86: =IF(G86="Fail","❌","") | G86: Pass | I86: Subhendu
A87: 2.7.6 | B87: Payment gateway config works | C87: Payment Module | D87: 🔴 Critical | E87: =IF(G87="Pass","✅","") | F87: =IF(G87="Fail","❌","") | G87: Not Run | I87: Subhendu
A88: 2.7.7 | B88: Email settings test works | C88: Communication Module | D88: 🟡 High | E88: =IF(G88="Pass","✅","") | F88: =IF(G88="Fail","❌","") | G88: Not Run | I88: Subhendu
A89: 2.7.8 | B89: Content management CRUD works | C89: Content Module | D89: 🟡 High | E89: =IF(G89="Pass","✅","") -> ✅ | F89: =IF(G89="Fail","❌","") | G89: Pass | I89: Subhendu
A90: 2.7.9 | B90: Review moderation works | C90: Review Module | D90: 🟡 High | E90: =IF(G90="Pass","✅","") | F90: =IF(G90="Fail","❌","") | G90: Not Run
A91: 2.7.10 | B91: System utilities (cache, backup) work | C91: Core Module | D91: 🟡 High | E91: =IF(G91="Pass","✅","") -> ✅ | F91: =IF(G91="Fail","❌","") | G91: Pass | I91: Subhendu
A92: 2.8 Real-time Features
A93: 2.8.1 | B93: Support chat messages send/receive | C93: Support chat | D93: 🔴 Critical | E93: =IF(G93="Pass","✅","") -> ✅ | F93: =IF(G93="Fail","❌","") | G93: Pass | I93: Subhendu
A94: 2.8.2 | B94: Chat shows online/offline status | C94: Support chat | D94: 🟡 High | E94: =IF(G94="Pass","✅","") | F94: =IF(G94="Fail","❌","") -> ❌ | G94: Fail | I94: Subhendu
A95: 2.8.3 | B95: Typing indicators display | C95: Support chat | D95: 🟢 Medium | E95: =IF(G95="Pass","✅","") | F95: =IF(G95="Fail","❌","") -> ❌ | G95: Fail | I95: Subhendu
A96: 2.8.4 | B96: Notifications appear in real-time | C96: Notification bell | D96: 🟡 High | E96: =IF(G96="Pass","✅","") | F96: =IF(G96="Fail","❌","") -> ❌ | G96: Fail | I96: Subhendu
A97: 2.8.5 | B97: AI suggestions appear in chat | C97: Support chat | D97: 🟡 High | E97: =IF(G97="Pass","✅","") | F97: =IF(G97="Fail","❌","") -> ❌ | G97: Fail | I97: Subhendu
A98: 2.8.6 | B98: Wheel spin result instant | C98: Wheel popup | D98: 🟡 High | E98: =IF(G98="Pass","✅","") | F98: =IF(G98="Fail","❌","") -> ❌ | G98: Fail | I98: Subhendu
A99: 2.9 Error Handling
A100: 2.9.1 | B100: 404 page displays for missing pages | C100: Error pages | D100: 🟡 High | E100: =IF(G100="Pass","✅","") -> ✅ | F100: =IF(G100="Fail","❌","") | G100: Pass | I100: Subhendu
A101: 2.9.2 | B101: 500 page displays for server errors | C101: Error pages | D101: 🟡 High | E101: =IF(G101="Pass","✅","") -> ✅ | F101: =IF(G101="Fail","❌","") | G101: Pass | I101: Subhendu
...

Sheet 3.Responsive
A1: 3.Responsive
A2: Use dropdown in "Result" column: Pass / Fail / Not Run / Blocked
A4: Test ID | B4: Test Case Description | C4: Page / Component | D4: Priority | E4: Pass | F4: Fail | G4: Result | H4: Notes / Bug Reference | I4: Tester
A5: 3.1 Mobile Devices (< 768px)
A6: 3.1.1 | B6: Homepage layout adapts | C6: iPhone SE (375px) | D6: 🔴 Critical | E6: =IF(G6="Pass","✅","") -> ✅ | F6: =IF(G6="Fail","❌","") | G6: Pass | I6: Subhendu
A7: 3.1.2 | B7: Navigation collapses to hamburger | C7: All pages | D7: 🔴 Critical | E7: =IF(G7="Pass","✅","") -> ✅ | F7: =IF(G7="Fail","❌","") | G7: Pass | I7: Subhendu
A8: 3.1.3 | B8: Product grid single column | C8: Product listing | D8: 🟡 High | E8: =IF(G8="Pass","✅","") -> ✅ | F8: =IF(G8="Fail","❌","") | G8: Pass | I8: Subhendu
A9: 3.1.4 | B9: Forms stack vertically | C9: All forms | D9: 🟡 High | E9: =IF(G9="Pass","✅","") -> ✅ | F9: =IF(G9="Fail","❌","") | G9: Pass | I9: Subhendu
A10: 3.1.5 | B10: Tables scroll horizontally or stack | C10: Admin tables | D10: 🟡 High | E10: =IF(G10="Pass","✅","") -> ✅ | F10: =IF(G10="Fail","❌","") | G10: Pass | I10: Subhendu
A11: 3.1.6 | B11: Buttons full width or touch-friendly | C11: All buttons | D11: 🟡 High | E11: =IF(G11="Pass","✅","") -> ✅ | F11: =IF(G11="Fail","❌","") | G11: Pass | I11: Subhendu
A12: 3.1.7 | B12: Text readable without zoom | C12: All pages | D12: 🔴 Critical | E12: =IF(G12="Pass","✅","") -> ✅ | F12: =IF(G12="Fail","❌","") | G12: Pass | I12: Subhendu
A13: 3.1.8 | B13: Images scale properly | C13: All images | D13: 🟡 High | E13: =IF(G13="Pass","✅","") -> ✅ | F13: =IF(G13="Fail","❌","") | G13: Pass | I13: Subhendu
A14: 3.1.9 | B14: Cart icon accessible | C14: Header | D14: 🔴 Critical | E14: =IF(G14="Pass","✅","") | F14: =IF(G14="Fail","❌","") -> ❌ | G14: Fail | H14: Cart icon is hidden in the mobile header and only accessible via the hamburger menu. | I14: Subhendu
A15: 3.1.10 | B15: Checkout flow usable | C15: Checkout | D15: 🔴 Critical | E15: =IF(G15="Pass","✅","") -> ✅ | F15: =IF(G15="Fail","❌","") | G15: Pass | I15: Subhendu
A16: 3.1.11 | B16: Admin sidebar collapsible | C16: Admin panel | D16: 🟡 High | E16: =IF(G16="Pass","✅","") -> ✅ | F16: =IF(G16="Fail","❌","") | G16: Pass | H16: Logout option is missing or hidden in the Admin Dashboard. | I16: Subhendu
A17: 3.1.12 | B17: Modal dialogs fit screen | C17: All modals | D17: 🟡 High | E17: =IF(G17="Pass","✅","") -> ✅ | F17: =IF(G17="Fail","❌","") | G17: Pass | I17: Subhendu
A18: 3.1.13 | B18: Footer stacks properly | C18: Footer | D18: 🟢 Medium | E18: =IF(G18="Pass","✅","") -> ✅ | F18: =IF(G18="Fail","❌","") | G18: Pass | I18: Subhendu
A19: 3.1.14 | B19: Touch targets minimum 44×44px | C19: All interactive | D19: 🔴 Critical | E19: =IF(G19="Pass","✅","") -> ✅ | F19: =IF(G19="Fail","❌","") | G19: Pass | I19: Subhendu
A20: 3.1.15 | B20: No horizontal scroll on mobile | C20: All pages | D20: 🔴 Critical | E20: =IF(G20="Pass","✅","") | F20: =IF(G20="Fail","❌","") -> ❌ | G20: Fail | H20: Horizontal scroll issue on mobile devices | I20: Subhendu
A21: 3.2 Tablet Devices (768px – 1024px)
A22: 3.2.1 | B22: Homepage layout adapts | C22: iPad (768px) | D22: 🟡 High | E22: =IF(G22="Pass","✅","") -> ✅ | F22: =IF(G22="Fail","❌","") | G22: Pass | I22: Subhendu
A23: 3.2.2 | B23: Navigation appropriate for tablet | C23: All pages | D23: 🟡 High | E23: =IF(G23="Pass","✅","") -> ✅ | F23: =IF(G23="Fail","❌","") | G23: Pass | I23: Subhendu
A24: 3.2.3 | B24: Product grid 2 columns | C24: Product listing | D24: 🟡 High | E24: =IF(G24="Pass","✅","") | F24: =IF(G24="Fail","❌","") -> ❌ | G24: Fail | H24: Product grid layout on Tablet fails to display in 2 columns. | I24: Subhendu
A25: 3.2.4 | B25: Forms 2-column where appropriate | C25: All forms | D25: 🟢 Medium | E25: =IF(G25="Pass","✅","") | F25: =IF(G25="Fail","❌","") -> ❌ | G25: Fail | H25: Forms fail to adapt to a 2-column layout on Tablet devices. | I25: Subhendu
A26: 3.2.5 | B26: Tables readable | C26: Admin tables | D26: 🟡 High | E26: =IF(G26="Pass","✅","") -> ✅ | F26: =IF(G26="Fail","❌","") | G26: Pass | I26: Subhendu
A27: 3.2.6 | B27: Dashboard widgets stack properly | C27: Dashboard | D27: 🟡 High | E27: =IF(G27="Pass","✅","") -> ✅ | F27: =IF(G27="Fail","❌","") | G27: Pass | I27: Subhendu
A28: 3.2.7 | B28: Sidebar navigation usable | C28: Admin/Customer | D28: 🟡 High | E28: =IF(G28="Pass","✅","") -> ✅ | F28: =IF(G28="Fail","❌","") | G28: Pass | I28: Subhendu
A29: 3.2.8 | B29: Images medium size | C29: All images | D29: 🟢 Medium | E29: =IF(G29="Pass","✅","") -> ✅ | F29: =IF(G29="Fail","❌","") | G29: Pass | I29: Subhendu
A30: 3.2.9 | B30: Modals centered properly | C30: All modals | D30: 🟢 Medium | E30: =IF(G30="Pass","✅","") -> ✅ | F30: =IF(G30="Fail","❌","") | G30: Pass | I30: Subhendu
A31: 3.2.10 | B31: Footer 2–3 columns | C31: Footer | D31: 🟢 Medium | E31: =IF(G31="Pass","✅","") | F31: =IF(G31="Fail","❌","") -> ❌ | G31: Fail | H31: Footer layout fails to utilize multi-column grid on Tablet/Desktop. | I31: Subhendu
A32: 3.3 Desktop Devices (> 1024px)
A33: 3.3.1 | B33: Homepage full layout | C33: 1366×768 | D33: 🟡 High | E33: =IF(G33="Pass","✅","") -> ✅ | F33: =IF(G33="Fail","❌","") | G33: Pass | I33: Subhendu
A34: 3.3.2 | B34: Navigation full horizontal | C34: All pages | D34: 🟡 High | E34: =IF(G34="Pass","✅","") -> ✅ | F34: =IF(G34="Fail","❌","") | G34: Pass | I34: Subhendu
A35: 3.3.3 | B35: Product grid 3–4 columns | C35: Product listing | D35: 🟡 High | E35: =IF(G35="Pass","✅","") -> ✅ | F35: =IF(G35="Fail","❌","") | G35: Pass | I35: Subhendu
A36: 3.3.4 | B36: Forms multi-column | C36: All forms | D36: 🟢 Medium | E36: =IF(G36="Pass","✅","") -> ✅ | F36: =IF(G36="Fail","❌","") | G36: Pass | I36: Subhendu
A37: 3.3.5 | B37: Tables full width | C37: Admin tables | D37: 🟡 High | E37: =IF(G37="Pass","✅","") -> ✅ | F37: =IF(G37="Fail","❌","") | G37: Pass | I37: Subhendu
A38: 3.3.6 | B38: Dashboard widgets grid | C38: Dashboard | D38: 🟡 High | E38: =IF(G38="Pass","✅","") -> ✅ | F38: =IF(G38="Fail","❌","") | G38: Pass | I38: Subhendu
A39: 3.3.7 | B39: Sidebar + content layout | C39: Admin/Customer | D39: 🟡 High | E39: =IF(G39="Pass","✅","") -> ✅ | F39: =IF(G39="Fail","❌","") | G39: Pass | I39: Subhendu
A40: 3.3.8 | B40: Images large/high-res | C40: All images | D40: 🟢 Medium | E40: =IF(G40="Pass","✅","") -> ✅ | F40: =IF(G40="Fail","❌","") | G40: Pass | I40: Subhendu
A41: 3.3.9 | B41: Modals with backdrop | C41: All modals | D41: 🟢 Medium | E41: =IF(G41="Pass","✅","") -> ✅ | F41: =IF(G41="Fail","❌","") | G41: Pass | I41: Subhendu
A42: 3.3.10 | B42: Footer full columns | C42: Footer | D42: 🟢 Medium | E42: =IF(G42="Pass","✅","") -> ✅ | F42: =IF(G42="Fail","❌","") | G42: Pass | I42: Subhendu
A43: 3.3.11 | B43: Layout on large screens | C43: 1920×1080 | D43: 🟡 High | E43: =IF(G43="Pass","✅","") -> ✅ | F43: =IF(G43="Fail","❌","") | G43: Pass | I43: Subhendu
A44: 3.3.12 | B44: No excessive white space | C44: All pages | D44: 🟢 Medium | E44: =IF(G44="Pass","✅","") -> ✅ | F44: =IF(G44="Fail","❌","") | G44: Pass | I44: Subhendu
A45: 3.4 Orientation Testing
A46: 3.4.1 | B46: Mobile portrait mode | C46: Mobile | D46: 🟡 High | E46: =IF(G46="Pass","✅","") -> ✅ | F46: =IF(G46="Fail","❌","") | G46: Pass | I46: Subhendu
A47: 3.4.2 | B47: Mobile landscape mode | C47: Mobile | D47: 🟡 High | E47: =IF(G47="Pass","✅","") | F47: =IF(G47="Fail","❌","") -> ❌ | G47: Fail | H47: Navigation Menu Disappears in Landscape Orientation | I47: Subhendu
A48: 3.4.3 | B48: Tablet portrait mode | C48: Tablet | D48: 🟢 Medium | E48: =IF(G48="Pass","✅","") -> ✅ | F48: =IF(G48="Fail","❌","") | G48: Pass | I48: Subhendu
A49: 3.4.4 | B49: Tablet landscape mode | C49: Tablet | D49: 🟢 Medium | E49: =IF(G49="Pass","✅","") -> ✅ | F49: =IF(G49="Fail","❌","") | G49: Pass | I49: Subhendu
A50: 3.4.5 | B50: Orientation change handled | C50: All mobile | D50: 🟡 High | E50: =IF(G50="Pass","✅","") | F50: =IF(G50="Fail","❌","") -> ❌ | G50: Fail | H50: Broken Layout Adjustment on Orientation Change | I50: Subhendu
A52: 📊 Section Summary | C52: Total | D52: Passed | E52: Failed | F52: Not Run | G52: Pass Rate
C53: =COUNTA(G5:G50) -> 42 | D53: =COUNTIF(G5:G50,"Pass") -> 35 | E53: =COUNTIF(G5:G50,"Fail") -> 7 | F53: =COUNTIF(G5:G50,"Not Run") -> 0 | G53: =IFERROR(COUNTIF(G5:G50,"Pass")/COUNTA(G5:G50),0) -> 0.83333333

Sheet 4.CrossBrowser
A1: 4.CrossBrowser
A2: Use dropdown in "Result" column: Pass / Fail / Not Run / Blocked
A4: Test ID | B4: Test Case Description | C4: Page / Component | D4: Priority | E4: Pass | F4: Fail | G4: Result | H4: Notes / Bug Reference | I4: Tester
A5: 4.1 Google Chrome
A6: 4.1.1 | B6: All pages render correctly | C6: Chrome Latest | D6: 🔴 Critical | E6: =IF(G6="Pass","✅","") | F6: =IF(G6="Fail","❌","") -> ❌ | G6: Fail | H6: Multiple 404 resource errors and a terminal JS exception in the drawWheel function are causing incomplete UI rendering. | I6: Subhendu
A7: 4.1.2 | B7: All JavaScript functions work | C7: Chrome Latest | D7: 🔴 Critical | E7: =IF(G7="Pass","✅","") | F7: =IF(G7="Fail","❌","") -> ❌ | G7: Fail | H7: Uncaught DOMException: Negative radius at line 640 and multiple 404 resource errors are breaking core JS features. | I7: Subhendu
A8: 4.1.3 | B8: CSS animations smooth | C8: Chrome Latest | D8: 🟢 Medium | E8: =IF(G8="Pass","✅","") | F8: =IF(G8="Fail","❌","") -> ❌ | G8: Fail | H8: Continuous JS exceptions and 404 resource failures are causing frame rate drops (jank) in CSS transitions. | I8: Subhendu
A9: 4.1.4 | B9: Forms submit correctly | C9: Chrome Latest | D9: 🔴 Critical | E9: =IF(G9="Pass","✅","") -> ✅ | F9: =IF(G9="Fail","❌","") | G9: Pass | H9: Contact form is functional and displays a success message, though global JS exceptions (IndexSizeError) persist in the console. | I9: Subhendu
A10: 4.1.5 | B10: Local storage works (cart) | C10: Chrome Latest | D10: 🔴 Critical | E10: =IF(G10="Pass","✅","") | F10: =IF(G10="Fail","❌","") -> ❌ | G10: Fail | H10: IndexSizeError in Console and missing cart data in Local Storage | I10: Subhendu
A11: 4.1.6 | B11: DevTools console clean (no errors) | C11: Chrome Latest | D11: 🟡 High | E11: =IF(G11="Pass","✅","") | F11: =IF(G11="Fail","❌","") -> ❌ | G11: Fail | H11: JavaScript Errors and Warnings in Console | I11: Subhendu
A12: 4.1.7 | B12: Previous version compatibility | C12: Chrome -1 | D12: 🟢 Medium | E12: =IF(G12="Pass","✅","") | F12: =IF(G12="Fail","❌","") -> ❌ | G12: Fail | H12: Persistent IndexSizeError and 404 image resource errors found in both latest and Chrome (Latest-1) version. | I12: Subhendu
A13: 4.1.8 | B13: Previous version compatibility | C13: Chrome -2 | D13: 🔵 Low | E13: =IF(G13="Pass","✅","") | F13: =IF(G13="Fail","❌","") -> ❌ | G13: Fail | H13: Critical JS logic error (radius provided is negative) is a legacy code issue, failing consistently in Chrome (Latest-2) as well. | I13: Subhendu
A14: 4.2 Mozilla Firefox
A15: 4.2.1 | B15: All pages render correctly | C15: Firefox Latest | D15: 🔴 Critical | E15: =IF(G15="Pass","✅","") | F15: =IF(G15="Fail","❌","") -> ❌ | G15: Fail | H15: Missing image assets (404) and failed Canvas rendering (IndexSizeError) causing incomplete UI. | I15: Subhendu
A16: 4.2.2 | B16: All JavaScript functions work | C16: Firefox Latest | D16: 🔴 Critical | E16: =IF(G16="Pass","✅","") | F16: =IF(G16="Fail","❌","") -> ❌ | G16: Fail | H16: Global JS exception at drawWheel stops script execution, breaking interactive features like filters and cart updates. | I16: Subhendu
A17: 4.2.3 | B17: CSS animations smooth | C17: Firefox Latest | D17: 🟢 Medium | E17: =IF(G17="Pass","✅","") | F17: =IF(G17="Fail","❌","") -> ❌ | G17: Fail | H17: Background JS errors are causing frame drops and jittery transitions in Firefox. | I17: Subhendu
A18: 4.2.4 | B18: Forms submit correctly | C18: Firefox Latest | D18: 🔴 Critical | E18: =IF(G18="Pass","✅","") -> ✅ | F18: =IF(G18="Fail","❌","") | G18: Pass | H18: Contact form submitted successfully with success message, despite global console errors. | I18: Subhendu
A19: 4.2.5 | B19: Local storage works (cart) | C19: Firefox Latest | D19: 🔴 Critical | E19: =IF(G19="Pass","✅","") | F19: =IF(G19="Fail","❌","") -> ❌ | G19: Fail | H19: Script errors prevent reliable data persistence in Firefox's Local Storage. | I19: Subhendu
A20: 4.2.6 | B20: DevTools console clean (no errors) | C20: Firefox Latest | D20: 🟡 High | E20: =IF(G20="Pass","✅","") | F20: =IF(G20="Fail","❌","") -> ❌ | G20: Fail | H20: Uncaught DOMException: Negative radius and multiple 404 Not Found errors detected. | I20: Subhendu
A21: 4.2.7 | B21: Previous version compatibility | C21: Firefox -1 | D21: 🟢 Medium | E21: =IF(G21="Pass","✅","") | F21: =IF(G21="Fail","❌","") -> ❌ | G21: Fail | H21: Identical JS logic errors and resource issues confirmed in previous Firefox versions. | I21: Subhendu
A22: 4.2.8 | B22: Previous version compatibility | C22: Firefox -2 | D22: 🔵 Low | E22: =IF(G22="Pass","✅","") | F22: =IF(G22="Fail","❌","") -> ❌ | G22: Fail | H22: Found persistent core errors that are not browser-version specific. | I22: Subhendu
A23: 4.3 Safari
A24: 4.3.1 | B24: All pages render correctly | C24: Safari Latest (Mac) | D24: 🔴 Critical | E24: =IF(G24="Pass","✅","") | F24: =IF(G24="Fail","❌","") -> ❌ | G24: Fail | H24: Missing image resources (404) and failed Canvas rendering (IndexSizeError) causing incomplete UI sections. | I24: Subhendu
A25: 4.3.2 | B25: All JavaScript functions work | C25: Safari Latest (Mac) | D25: 🔴 Critical | E25: =IF(G25="Pass","✅","") | F25: =IF(G25="Fail","❌","") -> ❌ | G25: Fail | H25: Global JS exception at drawWheel stops subsequent script execution, breaking interactive features. | I25: Subhendu
A26: 4.3.3 | B26: CSS animations smooth | C26: Safari Latest (Mac) | D26: 🟢 Medium | E26: =IF(G26="Pass","✅","") | F26: =IF(G26="Fail","❌","") -> ❌ | G26: Fail | H26: JS execution loops due to DOMException cause frame drops and stuttering in Safari transitions. | I26: Subhendu
A27: 4.3.4 | B27: Forms submit correctly | C27: Safari Latest (Mac) | D27: 🔴 Critical | E27: =IF(G27="Pass","✅","") -> ✅ | F27: =IF(G27="Fail","❌","") | G27: Pass | H27: Contact form is functional with success message, though background console errors persist. | I27: Subhendu
A28: 4.3.5 | B28: Local storage works (cart) | C28: Safari Latest (Mac) | D28: 🔴 Critical | E28: =IF(G28="Pass","✅","") | F28: =IF(G28="Fail","❌","") -> ❌ | G28: Fail | H28: Script errors are interrupting storage write operations; also blocked in Safari's Private Browsing mode. | I28: Subhendu
A29: 4.3.6 | B29: WebSockets work (Pusher) | C29: Safari Latest (Mac) | D29: 🔴 Critical | E29: =IF(G29="Pass","✅","") | F29: =IF(G29="Fail","❌","") -> ❌ | G29: Fail | H29: The critical JS error in init() prevents the Pusher client from establishing a real-time connection. | I29: Subhendu
A30: 4.3.7 | B30: iOS Safari compatibility | C30: iOS Latest | D30: 🔴 Critical | E30: =IF(G30="Pass","✅","") | F30: =IF(G30="Fail","❌","") -> ❌ | G30: Fail | H30: Identical layout breaks and console errors confirmed on iPhone/iPad (iOS Safari). | I30: Subhendu
A31: 4.3.8 | B31: iOS Safari previous version | C31: iOS -1 | D31: 🟢 Medium | E31: =IF(G31="Pass","✅","") | F31: =IF(G31="Fail","❌","") -> ❌ | G31: Fail | H31: Legacy JS logic errors (Negative radius) ensure failure on older iOS Safari versions as well. | I31: Subhendu
A32: 4.4 Microsoft Edge
A33: 4.4.1 | B33: All pages render correctly | C33: Edge Latest | D33: 🔴 Critical | E33: =IF(G33="Pass","✅","") | F33: =IF(G33="Fail","❌","") -> ❌ | G33: Fail | H33: Global JS logic errors and missing assets are persistent in Edge (Chromium) across all functional tests. | I33: Subhendu
A34: 4.4.2 | B34: All JavaScript functions work | C34: Edge Latest | D34: 🔴 Critical | E34: =IF(G34="Pass","✅","") | F34: =IF(G34="Fail","❌","") -> ❌ | G34: Fail | H34: Global JS logic errors and missing assets are persistent in Edge (Chromium) across all functional tests. | I34: Subhendu
A35: 4.4.3 | B35: CSS animations smooth | C35: Edge Latest | D35: 🟢 Medium | E35: =IF(G35="Pass","✅","") | F35: =IF(G35="Fail","❌","") -> ❌ | G35: Fail | H35: Global JS logic errors and missing assets are persistent in Edge (Chromium) across all functional tests. | I35: Subhendu
A36: 4.4.4 | B36: Forms submit correctly | C36: Edge Latest | D36: 🔴 Critical | E36: =IF(G36="Pass","✅","") -> ✅ | F36: =IF(G36="Fail","❌","") | G36: Pass | I36: Subhendu
A37: 4.4.5 | B37: Local storage works (cart) | C37: Edge Latest | D37: 🔴 Critical | E37: =IF(G37="Pass","✅","") | F37: =IF(G37="Fail","❌","") -> ❌ | G37: Fail | H37: Global JS logic errors and missing assets are persistent in Edge (Chromium) across all functional tests. | I37: Subhendu
A38: 4.4.6 | B38: DevTools console clean (no errors) | C38: Edge Latest | D38: 🟡 High | E38: =IF(G38="Pass","✅","") | F38: =IF(G38="Fail","❌","") -> ❌ | G38: Fail | H38: Global JS logic errors and missing assets are persistent in Edge (Chromium) across all functional tests. | I38: Subhendu
A39: 4.4.7 | B39: Previous version compatibility | C39: Edge -1 | D39: 🟢 Medium | E39: =IF(G39="Pass","✅","") | F39: =IF(G39="Fail","❌","") -> ❌ | G39: Fail | H39: Global JS logic errors and missing assets are persistent in Edge (Chromium) across all functional tests. | I39: Subhendu
A40: 4.5 Browser-Specific Features
A41: 4.5.1 | B41: Autofill works correctly | C41: All browsers | D41: 🟢 Medium | E41: =IF(G41="Pass","✅","") -> ✅ | F41: =IF(G41="Fail","❌","") | G41: Pass | I41: Subhendu
A42: 4.5.2 | B42: Password manager integration | C42: All browsers | D42: 🟢 Medium | E42: =IF(G42="Pass","✅","") -> ✅ | F42: =IF(G42="Fail","❌","") | G42: Pass | I42: Subhendu
A43: 4.5.3 | B43: Print styles work | C43: All browsers | D43: 🔵 Low | E43: =IF(G43="Pass","✅","") | F43: =IF(G43="Fail","❌","") -> ❌ | G43: Fail | H43: Critical UI issue where the print preview renders a blank/white page with no visible text or content. | I43: Subhendu
A44: 4.5.4 | B44: Dark mode respects OS setting | C44: All browsers | D44: 🟢 Medium | E44: =IF(G44="Pass","✅","") -> ✅ | F44: =IF(G44="Fail","❌","") | G44: Pass | I44: Subhendu
A45: 4.5.5 | B45: Zoom 150% layout holds | C45: All browsers | D45: 🟡 High | E45: =IF(G45="Pass","✅","") -> ✅ | F45: =IF(G45="Fail","❌","") | G45: Pass | I45: Subhendu
A46: 4.5.6 | B46: Zoom 200% layout holds | C46: All browsers | D46: 🟡 High | E46: =IF(G46="Pass","✅","") -> ✅ | F46: =IF(G46="Fail","❌","") | G46: Pass | I46: Subhendu
A48: 📊 Section Summary | C48: Total | D48: Passed | E48: Failed | F48: Not Run | G48: Pass Rate
C49: =COUNTA(G5:G46) -> 37 | D49: =COUNTIF(G5:G46,"Pass") -> 9 | E49: =COUNTIF(G5:G46,"Fail") -> 28 | F49: =COUNTIF(G5:G46,"Not Run") -> 0 | G49: =IFERROR(COUNTIF(G5:G46,"Pass")/COUNTA(G5:G46),0) -> 0.24324324

Sheet 5.Accessibility
A1: 5.Accessibility
A2: Use dropdown in "Result" column: Pass / Fail / Not Run / Blocked
A4: Test ID | B4: Test Case Description | C4: Page / Component | D4: Priority | E4: Pass | F4: Fail | G4: Result | H4: Notes / Bug Reference | I4: Tester
A5: 5.1 Keyboard Navigation
A6: 5.1.1 | B6: Tab through all interactive elements | C6: All pages | D6: 🔴 Critical | E6: =IF(G6="Pass","✅","") -> ✅ | F6: =IF(G6="Fail","❌","") | G6: Pass | I6: Subhendu
A7: 5.1.2 | B7: Shift+Tab reverses tab order | C7: All pages | D7: 🟡 High | E7: =IF(G7="Pass","✅","") -> ✅ | F7: =IF(G7="Fail","❌","") | G7: Pass | I7: Subhendu
A8: 5.1.3 | B8: Enter key activates buttons/links | C8: All pages | D8: 🔴 Critical | E8: =IF(G8="Pass","✅","") -> ✅ | F8: =IF(G8="Fail","❌","") | G8: Pass | I8: Subhendu
A9: 5.1.4 | B9: Spacebar activates buttons | C9: All pages | D9: 🟡 High | E9: =IF(G9="Pass","✅","") -> ✅ | F9: =IF(G9="Fail","❌","") | G9: Pass | I9: Subhendu
A10: 5.1.5 | B10: Arrow keys navigate menus | C10: Navigation | D10: 🟡 High | E10: =IF(G10="Pass","✅","") -> ✅ | F10: =IF(G10="Fail","❌","") | G10: Pass | I10: Subhendu
A11: 5.1.6 | B11: Escape key closes modals | C11: All modals | D11: 🔴 Critical | E11: =IF(G11="Pass","✅","") -> ✅ | F11: =IF(G11="Fail","❌","") | G11: Pass | I11: Subhendu
A12: 5.1.7 | B12: Focus visible on all elements | C12: All pages | D12: 🔴 Critical | E12: =IF(G12="Pass","✅","") -> ✅ | F12: =IF(G12="Fail","❌","") | G12: Pass | I12: Subhendu
A13: 5.1.8 | B13: Focus order is logical | C13: All pages | D13: 🟡 High | E13: =IF(G13="Pass","✅","") -> ✅ | F13: =IF(G13="Fail","❌","") | G13: Pass | I13: Subhendu
A14: 5.1.9 | B14: Skip to content link works | C14: All pages | D14: 🟡 High | E14: =IF(G14="Pass","✅","") -> ✅ | F14: =IF(G14="Fail","❌","") | G14: Pass | I14: Subhendu
A15: 5.1.10 | B15: No keyboard traps | C15: All pages | D15: 🔴 Critical | E15: =IF(G15="Pass","✅","") | F15: =IF(G15="Fail","❌","") -> ❌ | G15: Fail | H15: Navigation focus stuck in Calendar widget (Tab navigation failure). | I15: Subhendu
A16: 5.1.11 | B16: Form fields keyboard accessible | C16: All forms | D16: 🔴 Critical | E16: =IF(G16="Pass","✅","") -> ✅ | F16: =IF(G16="Fail","❌","") | G16: Pass | I16: Subhendu
A17: 5.1.12 | B17: Dropdown menus keyboard accessible | C17: All dropdowns | D17: 🟡 High | E17: =IF(G17="Pass","✅","") -> ✅ | F17: =IF(G17="Fail","❌","") | G17: Pass | I17: Subhendu
A18: 5.1.13 | B18: Date pickers keyboard accessible | C18: Forms | D18: 🟡 High | E18: =IF(G18="Pass","✅","") -> ✅ | F18: =IF(G18="Fail","❌","") | G18: Pass | I18: Subhendu
A19: 5.1.14 | B19: Custom components keyboard accessible | C19: All custom UI | D19: 🟡 High | E19: =IF(G19="Pass","✅","") -> ✅ | F19: =IF(G19="Fail","❌","") | G19: Pass | I19: Subhendu
A20: 5.1.15 | B20: Admin tables keyboard navigable | C20: Admin panels | D20: 🟡 High | E20: =IF(G20="Pass","✅","") -> ✅ | F20: =IF(G20="Fail","❌","") | G20: Pass | I20: Subhendu
A21: 5.2 Screen Reader Compatibility
A22: 5.2.1 | B22: Page title announced | C22: NVDA/VoiceOver | D22: 🔴 Critical | E22: =IF(G22="Pass","✅","") -> ✅ | F22: =IF(G22="Fail","❌","") | G22: Pass | I22: Subhendu
A23: 5.2.2 | B23: Navigation landmarks identified | C23: NVDA/VoiceOver | D23: 🟡 High | E23: =IF(G23="Pass","✅","") -> ✅ | F23: =IF(G23="Fail","❌","") | G23: Pass | I23: Subhendu
A24: 5.2.3 | B24: Form labels announced | C24: NVDA/VoiceOver | D24: 🔴 Critical | E24: =IF(G24="Pass","✅","") -> ✅ | F24: =IF(G24="Fail","❌","") | G24: Pass | I24: Subhendu
A25: 5.2.4 | B25: Error messages announced | C25: NVDA/VoiceOver | D25: 🔴 Critical | E25: =IF(G25="Pass","✅","") | F25: =IF(G25="Fail","❌","") -> ❌ | G25: Fail | H25: Screen reader does not announce form validation error messages automatically. | I25: Subhendu
A26: 5.2.5 | B26: Success messages announced | C26: NVDA/VoiceOver | D26: 🟡 High | E26: =IF(G26="Pass","✅","") -> ✅ | F26: =IF(G26="Fail","❌","") | G26: Pass | I26: Subhendu
A27: 5.2.6 | B27: Images have alt text | C27: NVDA/VoiceOver | D27: 🔴 Critical | E27: =IF(G27="Pass","✅","") -> ✅ | F27: =IF(G27="Fail","❌","") | G27: Pass | I27: Subhendu
A28: 5.2.7 | B28: Tables have proper headers | C28: NVDA/VoiceOver | D28: 🟡 High | E28: =IF(G28="Pass","✅","") -> ✅ | F28: =IF(G28="Fail","❌","") | G28: Pass | I28: Subhendu
A29: 5.2.8 | B29: Links have descriptive text | C29: NVDA/VoiceOver | D29: 🟡 High | E29: =IF(G29="Pass","✅","") -> ✅ | F29: =IF(G29="Fail","❌","") | G29: Pass | I29: Subhendu
A30: 5.2.9 | B30: Buttons have accessible names | C30: NVDA/VoiceOver | D30: 🔴 Critical | E30: =IF(G30="Pass","✅","") -> ✅ | F30: =IF(G30="Fail","❌","") | G30: Pass | I30: Subhendu
A31: 5.2.10 | B31: Dynamic content announced | C31: NVDA/VoiceOver | D31: 🟡 High | E31: =IF(G31="Pass","✅","") -> ✅ | F31: =IF(G31="Fail","❌","") | G31: Pass | I31: Subhendu
A32: 5.2.11 | B32: Modal dialogs announced | C32: NVDA/VoiceOver | D32: 🟡 High | E32: =IF(G32="Pass","✅","") | F32: =IF(G32="Fail","❌","") -> ❌ | G32: Fail | H32: Screen reader fails to announce and move focus to the "Add to Cart" confirmation modal. | I32: Subhendu
A33: 5.2.12 | B33: Password toggle announced | C33: NVDA/VoiceOver | D33: 🟢 Medium | E33: =IF(G33="Pass","✅","") -> ✅ | F33: =IF(G33="Fail","❌","") | G33: Pass | I33: Subhendu
A34: 5.3 WCAG 2.1 Level AA Compliance
A35: 5.3.1 | B35: Color contrast ratio ≥ 4.5:1 | C35: 1.4.3 Contrast | D35: 🔴 Critical | E35: =IF(G35="Pass","✅","") | F35: =IF(G35="Fail","❌","") -> ❌ | G35: Fail | H35: Multiple elements across the homepage fail to meet the WCAG 2.1 AA standard contrast ratio of 4.5:1. | I35: Subhendu
A36: 5.3.2 | B36: Text resizable to 200% | C36: 1.4.4 Resize Text | D36: 🔴 Critical | E36: =IF(G36="Pass","✅","") -> ✅ | F36: =IF(G36="Fail","❌","") | G36: Pass | I36: Subhendu
A37: 5.3.3 | B37: Images of text avoided | C37: 1.4.5 Images of Text | D37: 🟡 High | E37: =IF(G37="Pass","✅","") -> ✅ | F37: =IF(G37="Fail","❌","") | G37: Pass | I37: Subhendu
A38: 5.3.4 | B38: Color not only means of conveying info | C38: 1.4.1 Use of Color | D38: 🔴 Critical | E38: =IF(G38="Pass","✅","") -> ✅ | F38: =IF(G38="Fail","❌","") | G38: Pass | I38: Subhendu
A39: 5.3.5 | B39: Audio auto-play disabled | C39: 1.4.2 Audio Control | D39: 🟡 High | E39: =IF(G39="Pass","✅","") -> ✅ | F39: =IF(G39="Fail","❌","") | G39: Pass | I39: Subhendu
A40: 5.3.6 | B40: Headings describe content | C40: 2.4.6 Headings | D40: 🟡 High | E40: =IF(G40="Pass","✅","") -> ✅ | F40: =IF(G40="Fail","❌","") | G40: Pass | I40: Subhendu
A41: 5.3.7 | B41: Focus visible indicator | C41: 2.4.7 Focus Visible | D41: 🔴 Critical | E41: =IF(G41="Pass","✅","") -> ✅ | F41: =IF(G41="Fail","❌","") | G41: Pass | I41: Subhendu
A42: 5.3.8 | B42: Language of page defined in HTML | C42: 3.1.1 Language | D42: 🟡 High | E42: =IF(G42="Pass","✅","") -> ✅ | F42: =IF(G42="Fail","❌","") | G42: Pass | I42: Subhendu
A43: 5.3.9 | B43: Consistent navigation across pages | C43: 3.2.3 Consistent Nav | D43: 🟡 High | E43: =IF(G43="Pass","✅","") -> ✅ | F43: =IF(G43="Fail","❌","") | G43: Pass | I43: Subhendu
A44: 5.3.10 | B44: Consistent identification of components | C44: 3.2.4 Consistent ID | D44: 🟡 High | E44: =IF(G44="Pass","✅","") -> ✅ | F44: =IF(G44="Fail","❌","") | G44: Pass | I44: Subhendu
A45: 5.3.11 | B45: Error prevention on forms | C45: 3.3.4 Error Prevention | D45: 🔴 Critical | E45: =IF(G45="Pass","✅","") -> ✅ | F45: =IF(G45="Fail","❌","") | G45: Pass | I45: Subhendu
A46: 5.3.12 | B46: Help available for forms | C46: 3.3.5 Help | D46: 🟢 Medium | E46: =IF(G46="Pass","✅","") | F46: =IF(G46="Fail","❌","") -> ❌ | G46: Fail | H46: Input fields (Password, Date, etc.) lack descriptive instructions, placeholders with examples, or helper tooltips to guide the user. | I46: Subhendu
A47: 5.4 Visual Accessibility
A48: 5.4.1 | B48: Focus indicators high contrast | C48: All pages | D48: 🔴 Critical | E48: =IF(G48="Pass","✅","") -> ✅ | F48: =IF(G48="Fail","❌","") | G48: Pass | I48: Subhendu
A49: 5.4.2 | B49: Link identification clear | C49: All pages | D49: 🟡 High | E49: =IF(G49="Pass","✅","") -> ✅ | F49: =IF(G49="Fail","❌","") | G49: Pass | I49: Subhendu
A50: 5.4.3 | B50: Error states visually clear | C50: All forms | D50: 🟡 High | E50: =IF(G50="Pass","✅","") -> ✅ | F50: =IF(G50="Fail","❌","") | G50: Pass | I50: Subhendu
A51: 5.4.4 | B51: Required fields indicated | C51: All forms | D51: 🟡 High | E51: =IF(G51="Pass","✅","") -> ✅ | F51: =IF(G51="Fail","❌","") | G51: Pass | I51: Subhendu
A52: 5.4.5 | B52: Loading states visible | C52: Async actions | D52: 🟡 High | E52: =IF(G52="Pass","✅","") -> ✅ | F52: =IF(G52="Fail","❌","") | G52: Pass | I52: Subhendu
A53: 5.4.6 | B53: Disabled states visually clear | C53: All pages | D53: 🟡 High | E53: =IF(G53="Pass","✅","") | F53: =IF(G53="Fail","❌","") | G53: Not Run
A54: 5.4.7 | B54: Active nav states clear | C54: Navigation | D54: 🟢 Medium | E54: =IF(G54="Pass","✅","") | F54: =IF(G54="Fail","❌","") | G54: Not Run
A56: 📊 Section Summary | C56: Total | D56: Passed | E56: Failed | F56: Not Run | G56: Pass Rate
C57: =COUNTA(G5:G54) -> 46 | D57: =COUNTIF(G5:G54,"Pass") -> 39 | E57: =COUNTIF(G5:G54,"Fail") -> 5 | F57: =COUNTIF(G5:G54,"Not Run") -> 2 | G57: =IFERROR(COUNTIF(G5:G54,"Pass")/COUNTA(G5:G54),0) -> 0.84782609

Sheet 6.Performance
A1: 6.Performance
A2: Use dropdown in "Result" column: Pass / Fail / Not Run / Blocked
A4: Test ID | B4: Test Case Description | C4: Page / Component | D4: Priority | E4: Pass | F4: Fail | G4: Result | H4: Notes / Bug Reference | I4: Tester
A5: 6.1 Page Load Performance
A6: 6.1.1 | B6: First Contentful Paint (FCP) < 1.5s | C6: Homepage | D6: 🔴 Critical | E6: =IF(G6="Pass","✅","") -> ✅ | F6: =IF(G6="Fail","❌","") | G6: Pass | H6: Target: < 1.5s । Result 657 ms | I6: Subhendu
A7: 6.1.2 | B7: Largest Contentful Paint (LCP) < 2.5s | C7: Homepage | D7: 🔴 Critical | E7: =IF(G7="Pass","✅","") -> ✅ | F7: =IF(G7="Fail","❌","") | G7: Pass | H7: Target: < 2.5s | Result 697 ms | I7: Subhendu
A8: 6.1.3 | B8: Time to Interactive (TTI) < 3.5s | C8: Homepage | D8: 🔴 Critical | E8: =IF(G8="Pass","✅","") -> ✅ | F8: =IF(G8="Fail","❌","") | G8: Pass | H8: Target: < 3.5s । Result ~700 ms (Estimated) | I8: Subhendu
A9: 6.1.4 | B9: Cumulative Layout Shift (CLS) < 0.1 | C9: Homepage | D9: 🔴 Critical | E9: =IF(G9="Pass","✅","") -> ✅ | F9: =IF(G9="Fail","❌","") | G9: Pass | H9: Target: < 0.1 | Result 0.03 | I9: Subhendu
A10: 6.1.5 | B10: Total Blocking Time (TBT) < 300ms | C10: Homepage | D10: 🟡 High | E10: =IF(G10="Pass","✅","") -> ✅ | F10: =IF(G10="Fail","❌","") | G10: Pass | H10: Target: < 300ms । Result 125 ms | I10: Subhendu
A11: 6.1.6 | B11: First Contentful Paint (FCP) < 1.5s | C11: Product listing | D11: 🟡 High | E11: =IF(G11="Pass","✅","") -> ✅ | F11: =IF(G11="Fail","❌","") | G11: Pass | H11: Target: < 1.5s । Result 718 ms (0.7s) | I11: Subhendu
A12: 6.1.7 | B12: Largest Contentful Paint (LCP) < 2.5s | C12: Product listing | D12: 🟡 High | E12: =IF(G12="Pass","✅","") -> ✅ | F12: =IF(G12="Fail","❌","") | G12: Pass | H12: Target: < 2.5s । Result 1,661 ms (1.7s) | I12: Subhendu
A13: 6.1.8 | B13: First Contentful Paint (FCP) < 1.5s | C13: Checkout | D13: 🔴 Critical | E13: =IF(G13="Pass","✅","") -> ✅ | F13: =IF(G13="Fail","❌","") | G13: Pass | H13: Target: < 1.5s । Result 459 ms (0.4s) | I13: Subhendu
A14: 6.1.9 | B14: Time to Interactive (TTI) < 2.0s | C14: Checkout | D14: 🔴 Critical | E14: =IF(G14="Pass","✅","") -> ✅ | F14: =IF(G14="Fail","❌","") | G14: Pass | H14: Target: < 2.0s । Result ~0.5s (Est.) | I14: Subhendu
A15: 6.1.10 | B15: Admin dashboard load < 3.0s | C15: Admin | D15: 🟡 High | E15: =IF(G15="Pass","✅","") | F15: =IF(G15="Fail","❌","") | G15: Not Run | H15: Target: < 3.0s । Result 2.0 s (Speed Index) | I15: Subhendu
A16: 6.2 Resource Loading
A17: 6.2.1 | B17: Images lazy loaded on scroll | C17: Product listing | D17: 🟡 High | E17: =IF(G17="Pass","✅","") -> ✅ | F17: =IF(G17="Fail","❌","") | G17: Pass | H17: Images load dynamically upon scrolling.
A18: 6.2.2 | B18: Images optimized (WebP/AVIF format) | C18: All images | D18: 🟡 High | E18: =IF(G18="Pass","✅","") | F18: =IF(G18="Fail","❌","") | G18: Not Run | H18: Found images in JPEG/PNG format; WebP/AVIF is recommended.
A19: 6.2.3 | B19: CSS files minified | C19: All pages | D19: 🟡 High | E19: =IF(G19="Pass","✅","") -> ✅ | F19: =IF(G19="Fail","❌","") | G19: Pass | H19: Automated Audit - Lighthouse
A20: 6.2.4 | B20: JavaScript files minified | C20: All pages | D20: 🟡 High | E20: =IF(G20="Pass","✅","") -> ✅ | F20: =IF(G20="Fail","❌","") | G20: Pass | H20: Automated Audit - Lighthouse
A21: 6.2.5 | B21: No render-blocking resources | C21: All pages | D21: 🔴 Critical | E21: =IF(G21="Pass","✅","") -> ✅ | F21: =IF(G21="Fail","❌","") | G21: Pass | H21: No render blocking resource found.
A22: 6.2.6 | B22: Critical CSS inlined above fold | C22: Above fold | D22: 🟢 Medium | E22: =IF(G22="Pass","✅","") | F22: =IF(G22="Fail","❌","") -> ❌ | G22: Fail | H22: Stylesheets are loaded externally, not inlined.
A23: 6.2.7 | B23: Fonts loaded efficiently (font-display) | C23: All pages | D23: 🟡 High | E23: =IF(G23="Pass","✅","") | F23: =IF(G23="Fail","❌","") | G23: Not Run | H23: font-display: Text loading is delayed because you are not using swap.
A24: 6.2.8 | B24: Third-party scripts deferred | C24: External scripts | D24: 🟡 High | E24: =IF(G24="Pass","✅","") -> ✅ | F24: =IF(G24="Fail","❌","") | G24: Pass | H24: There is no problem with third-party script loading.
A25: 6.2.9 | B25: No unused JavaScript loaded | C25: All pages | D25: 🟢 Medium | E25: =IF(G25="Pass","✅","") | F25: =IF(G25="Fail","❌","") -> ❌ | G25: Fail | H25: The coverage audit found that up to 88.6% of the main JS files and 99.2% of the CSS files were loading unused code. This is slowing down the page loading speed.
A26: 6.2.10 | B26: No unused CSS loaded | C26: All pages | D26: 🟢 Medium | E26: =IF(G26="Pass","✅","") | F26: =IF(G26="Fail","❌","") -> ❌ | G26: Fail | H26: Unused code found in Font-Awesome and App CSS.
A27: 6.3 Interaction Performance
A28: 6.3.1 | B28: Button click response < 100ms | C28: All buttons | D28: 🟡 High | E28: =IF(G28="Pass","✅","") -> ✅ | F28: =IF(G28="Fail","❌","") | G28: Pass | H28: Result 22.27 ms | The interaction response time is well below 100ms. | I28: Subhendu
A29: 6.3.2 | B29: Dropdown opens < 100ms | C29: All dropdowns | D29: 🟡 High | E29: =IF(G29="Pass","✅","") -> ✅ | F29: =IF(G29="Fail","❌","") | G29: Pass | H29: Result 21.65 ms | I29: Subhendu
A30: 6.3.3 | B30: Modal opens < 200ms | C30: All modals | D30: 🟡 High | E30: =IF(G30="Pass","✅","") -> ✅ | F30: =IF(G30="Fail","❌","") | G30: Pass | H30: The interaction time for modal opening is recorded at an average of 17.2 ms, which is much faster than the 200 ms limit. | I30: Subhendu
A31: 6.3.4 | B31: Page transition < 300ms | C31: Navigation | D31: 🟡 High | E31: =IF(G31="Pass","✅","") -> ✅ | F31: =IF(G31="Fail","❌","") | G31: Pass | H31: The new page transition took 2,253 ms after clicking on the link, which is much higher than the 300 ms limit. | I31: Subhendu
A32: 6.3.5 | B32: Form validation instant (< 100ms) | C32: All forms | D32: 🟡 High | E32: =IF(G32="Pass","✅","") -> ✅ | F32: =IF(G32="Fail","❌","") | G32: Pass | H32: Tested multiple times (6 steps). The maximum response time was 24.87 ms and the lowest was 1.58 ms. All were below the 100 ms limit. | I32: Subhendu
A33: 6.3.6 | B33: Search results appear < 500ms | C33: Search | D33: 🟡 High | E33: =IF(G33="Pass","✅","") -> ✅ | F33: =IF(G33="Fail","❌","") | G33: Pass | H33: Result 16.52 ms | I33: Subhendu
A34: 6.3.7 | B34: Cart update instant <100 ms | C34: Cart actions | D34: 🔴 Critical | E34: =IF(G34="Pass","✅","") -> ✅ | F34: =IF(G34="Fail","❌","") | G34: Pass | H34: 23.63 ms | I34: Subhendu
A35: 6.3.8 | B35: Filter apply < 500ms | C35: Product filters | D35: 🟡 High | E35: =IF(G35="Pass","✅","") -> ✅ | F35: =IF(G35="Fail","❌","") | G35: Pass | I35: Subhendu
A36: 6.3.9 | B36: Sort change < 300ms | C36: Product sort | D36: 🟡 High | E36: =IF(G36="Pass","✅","") -> ✅ | F36: =IF(G36="Fail","❌","") | G36: Pass | H36: 25.33 ms | I36: Subhendu
A37: 6.3.10 | B37: Animations run at 60fps | C37: All animations | D37: 🟢 Medium | E37: =IF(G37="Pass","✅","") | F37: =IF(G37="Fail","❌","") -> ❌ | G37: Fail | H37: The frame rate is recorded at 29.9 FPS during scrolling and animation. Rendering performance is lower than target due to GPU Raster turned off. | I37: Subhendu
A38: 6.4 Network Performance
A39: 6.4.1 | B39: Homepage loads on Slow 3G | C39: Slow 3G | D39: 🟡 High | E39: =IF(G39="Pass","✅","") -> ✅ | F39: =IF(G39="Fail","❌","") | G39: Pass | H39: Throttle in DevTools | Result 3.50s = Manual Slow 3G profile (400kbps) tested. The load time is 3.3 seconds, which is extremely fast and perfect. | I39: Subhendu
A40: 6.4.2 | B40: Product page loads on Slow 3G | C40: Slow 3G | D40: 🟡 High | E40: =IF(G40="Pass","✅","") | F40: =IF(G40="Fail","❌","") | G40: Not Run | H40: Throttle in DevTools | 3.91s (Finish) | I40: Subhendu
A41: 6.4.3 | B41: Checkout works on Slow 3G | C41: Slow 3G | D41: 🔴 Critical | E41: =IF(G41="Pass","✅","") | F41: =IF(G41="Fail","❌","") | G41: Not Run | H41: Throttle in DevTools | 3.94s (Finish) | I41: Subhendu
A42: 6.4.4 | B42: Offline handling (cached pages shown) | C42: Offline | D42: 🟢 Medium | E42: =IF(G42="Pass","✅","") | F42: =IF(G42="Fail","❌","") -> ❌ | G42: Fail | H42: When the page is reloaded in offline mode, the browser's default 'No Internet' (Dinosaur) page is displayed. The site does not support offline cache. | I42: Subhendu
A43: 6.4.5 | B43: Reconnection after going offline | C43: Offline → Online | D43: 🟢 Medium | E43: =IF(G43="Pass","✅","") | F43: =IF(G43="Fail","❌","") -> ❌ | G43: Fail | I43: Subhendu
A44: 6.4.6 | B44: API calls cached appropriately | C44: All API | D44: 🟢 Medium | E44: =IF(G44="Pass","✅","") -> ✅ | F44: =IF(G44="Fail","❌","") | G44: Pass | I44: Subhendu
A45: 6.4.7 | B45: No failed requests in Network tab | C45: All pages | D45: 🔴 Critical | E45: =IF(G45="Pass","✅","") | F45: =IF(G45="Fail","❌","") | G45: Not Run | H45: F12 → Network tab | I45: Subhendu
A46: 6.4.8 | B46: HTTP/2 or HTTP/3 protocol used | C46: All requests | D46: 🟡 High | E46: =IF(G46="Pass","✅","") | F46: =IF(G46="Fail","❌","") | G46: Not Run | H46: F12 → Network → Protocol | I46: Subhendu
A47: 6.5 Memory & CPU
A48: 6.5.1 | B48: No memory leaks during long session | C48: All pages | D48: 🟡 High | E48: =IF(G48="Pass","✅","") | F48: =IF(G48="Fail","❌","") -> ❌ | G48: Fail | H48: DevTools → Memory । Result +18.8 MB । In 5 minutes of intensive use, the memory has increased from 11.2 MB to 30 MB, which is a sign of abnormal memory usage. | I48: Subhendu
A49: 6.5.2 | B49: CPU usage reasonable | C49: All pages | D49: 🟡 High | E49: =IF(G49="Pass","✅","") -> ✅ | F49: =IF(G49="Fail","❌","") | G49: Pass | H49: DevTools → Performance। 0.1% - 0.7% (Idle) The CPU usage rate is extremely negligible when the page is stationary, which proves the stability of the system. | I49: Subhendu
A50: 6.5.3 | B50: No excessive DOM nodes (< 1500) | C50: All pages | D50: 🟢 Medium | E50: =IF(G50="Pass","✅","") -> ✅ | F50: =IF(G50="Fail","❌","") | G50: Pass | H50: Lighthouse audit । There is no warning in the report, so the element number is below 1500. | I50: Subhendu
A51: 6.5.4 | B51: Garbage collection works properly | C51: Long sessions | D51: 🟢 Medium | E51: =IF(G51="Pass","✅","") | F51: =IF(G51="Fail","❌","") -> ❌ | G51: Fail | H51: Even after manually collecting 'garbage', the memory is not decreasing significantly, which indicates a 'memory leak'. | I51: Subhendu
A52: 6.5.5 | B52: No frozen/unresponsive tabs | C52: All pages | D52: 🔴 Critical | E52: =IF(G52="Pass","✅","") | F52: =IF(G52="Fail","❌","") -> ❌ | G52: Fail | H52: 22.47s Session । Session recordings showed that the main thread was busy for a long time. The tab becomes unresponsive due to the 669ms presentation delay and the looped long task. | I52: Subhendu
A54: 📊 Section Summary | C54: Total | D54: Passed | E54: Failed | F54: Not Run | G54: Pass Rate
C55: =COUNTA(G5:G52) -> 43 | D55: =COUNTIF(G5:G52,"Pass") -> 27 | E55: =COUNTIF(G5:G52,"Fail") -> 9 | F55: =COUNTIF(G5:G52,"Not Run") -> 7 | G55: =IFERROR(COUNTIF(G5:G52,"Pass")/COUNTA(G5:G52),0) -> 0.62790698

Sheet 🐛 Bug Log
A1: 🐛 Bug Report Log - Laravel Voucher App QA
A2: Log all failed test cases here with details for developer handoff
A3: Bug ID | B3: Test ID | C3: Bug Description | D3: Page/Component | E3: Priority | F3: Browser | G3: Device | H3: Steps to Reproduce | I3: Expected Result | J3: Actual Result | K3: Status
A4: BUG-001 | B4: TC-01

Sheet 📝 Test Report
A1: 📝 QA Test Report — Laravel Voucher Application
B4: 📊 TEST EXECUTION SUMMARY
B5: Total Tests | C5: =COUNTA('1.UI Visual'!G:G)+COUNTA('2.Functional'!G:G)+COUNTA('3.Responsive'!G:G)+COUNTA('4.CrossBrowser'!G:G)+COUNTA('5.Accessibility'!G:G)+COUNTA('6.Performance'!G:G)-6 -> 323
B6: Passed ✅ | C6: =COUNTIF('1.UI Visual'!G:G,"Pass")+COUNTIF('2.Functional'!G:G,"Pass")+COUNTIF('3.Responsive'!G:G,"Pass")+COUNTIF('4.CrossBrowser'!G:G,"Pass")+COUNTIF('5.Accessibility'!G:G,"Pass")+COUNTIF('6.Performance'!G:G,"Pass") -> 219
B7: Failed ❌ | C7: =COUNTIF('1.UI Visual'!G:G,"Fail")+COUNTIF('2.Functional'!G:G,"Fail")+COUNTIF('3.Responsive'!G:G,"Fail")+COUNTIF('4.CrossBrowser'!G:G,"Fail")+COUNTIF('5.Accessibility'!G:G,"Fail")+COUNTIF('6.Performance'!G:G,"Fail") -> 75
B8: Not Run ⬜ | C8: =COUNTIF('1.UI Visual'!G:G,"Not Run")+COUNTIF('2.Functional'!G:G,"Not Run")+COUNTIF('3.Responsive'!G:G,"Not Run")+COUNTIF('4.CrossBrowser'!G:G,"Not Run")+COUNTIF('5.Accessibility'!G:G,"Not Run")+COUNTIF('6.Performance'!G:G,"Not Run") -> 17
B9: Pass Rate | C9: =IFERROR(C6/C5,0) -> 0.67801858
B10: Overall Status | C10: =IF(C7>0,"❌ FAIL",IF(C9>=0.95,"✅ PASS","⚠️ CONDITIONAL PASS")) -> ❌ FAIL
B27: ✍️ SIGN-OFF
B28: Role | C28: Name | D28: Date | E28: Signature | F28: Comments
B29: QA Tester
B30: QA Lead
B31: Frontend Lead
B32: Product Owner
